idutils/__init__.py
idutils/detectors.py
idutils/ext.py
idutils/normalizers.py
idutils/proxies.py
idutils/schemes.py
idutils/utils.py
idutils/validators.py
idutils-1.5.1.dist-info/licenses/AUTHORS.rst
idutils-1.5.1.dist-info/licenses/LICENSE
idutils-1.5.1.dist-info/METADATA
idutils-1.5.1.dist-info/WHEEL
idutils-1.5.1.dist-info/top_level.txt
idutils-1.5.1.dist-info/RECORD
